beda/__init__.py
beda-0.0.1.dist-info/licenses/LICENSE
beda-0.0.1.dist-info/METADATA
beda-0.0.1.dist-info/WHEEL
beda-0.0.1.dist-info/top_level.txt
beda-0.0.1.dist-info/RECORD
