Metadata-Version: 2.4
Name: beda
Version: 0.0.1
Summary: Binary Epigraphic Data Archive (BEDA) - Python utilities for template generation.
Author-email: Andrea Marruzzo <amarruzzo@gmail.com>
License: MIT
Classifier: Programming Language :: Python :: 3
Classifier: License :: OSI Approved :: MIT License
Classifier: Topic :: Sociology :: History
Classifier: Topic :: Text Processing :: Markup :: XML
License-File: LICENSE
Dynamic: license-file
